git_gopher
test
