Metadata-Version: 2.1
Name: git-gopher
Version: 0.5.5
Summary: Improving the Git CLI experience with fzf
Home-page: https://github.com/derekhamilton/git-gopher
Author: Derek Hamilton
License: UNKNOWN
Project-URL: Source, https://github.com/derekhamilton/git-gopher
Keywords: git git-cli git-client linux fzf cli command-line
Platform: UNKNOWN
Classifier: Development Status :: 4 - Beta
Classifier: Intended Audience :: Developers
Classifier: License :: OSI Approved :: MIT License
Classifier: Programming Language :: Python :: 3.5
Classifier: Programming Language :: Python :: 3.6
Classifier: Programming Language :: Python :: 3.7
Requires-Python: >=3.5
